pynoc/__init__.py
pynoc/apc.py
pynoc/cisco.py
pynoc-1.6.3.dist-info/METADATA
pynoc-1.6.3.dist-info/RECORD
pynoc-1.6.3.dist-info/WHEEL
pynoc-1.6.3.dist-info/top_level.txt
