Metadata-Version: 2.1
Name: pynoc
Version: 1.6.3
Summary: Network Operation Center gear
Home-page: http://github.com/SimplicityGuy/pynoc
Author: Robert Wlodarczyk
Author-email: robert@simplicityguy.com
License: Apache License 2.0
Keywords: instrument,switch,pdu,Cisco,APC,network gear
Platform: UNKNOWN
Classifier: Development Status :: 5 - Production/Stable
Classifier: Environment :: Console
Classifier: Intended Audience :: Developers
Classifier: License :: OSI Approved :: Apache Software License
Classifier: Programming Language :: Python :: 2.7
Classifier: Programming Language :: Python :: 3.3
Classifier: Programming Language :: Python :: 3.4
Classifier: Programming Language :: Python :: 3.5
Classifier: Programming Language :: Python :: 3.6
Classifier: Topic :: System :: Hardware
Classifier: Topic :: System :: Networking
Requires-Dist: pysnmp
Requires-Dist: netaddr
Requires-Dist: netmiko
Requires-Dist: retrying
